{
	"Version": 3,
	"Parameters": [
		{
			"Id": "chashou",
			"GroupId": "",
			"Name": "叉手"
		},
		{
			"Id": "zhuanshen",
			"GroupId": "",
			"Name": "转身"
		},
		{
			"Id": "GZL22679150",
			"GroupId": "",
			"Name": "水印"
		},
		{
			"Id": "ParamAngleX",
			"GroupId": "",
			"Name": "角度 X"
		},
		{
			"Id": "ParamAngleY",
			"GroupId": "",
			"Name": "角度 Y"
		},
		{
			"Id": "ParamAngleZ",
			"GroupId": "",
			"Name": "角度 Z"
		},
		{
			"Id": "ParamEyeLOpen",
			"GroupId": "",
			"Name": "左眼　开闭"
		},
		{
			"Id": "Param",
			"GroupId": "",
			"Name": "耳朵物理"
		},
		{
			"Id": "ParamEyeROpen",
			"GroupId": "",
			"Name": "右眼"
		},
		{
			"Id": "ParamEyeBallX",
			"GroupId": "",
			"Name": "眼珠 X"
		},
		{
			"Id": "ParamEyeBallY",
			"GroupId": "",
			"Name": "眼珠 Y"
		},
		{
			"Id": "ParamBrowLY",
			"GroupId": "",
			"Name": "左眉上下"
		},
		{
			"Id": "ParamBrowRY",
			"GroupId": "",
			"Name": "右眉　上下"
		},
		{
			"Id": "ParamMouthForm",
			"GroupId": "",
			"Name": "嘴　变形"
		},
		{
			"Id": "ParamMouthOpenY",
			"GroupId": "",
			"Name": "嘴　张开和闭合"
		},
		{
			"Id": "ParamBodyAngleX",
			"GroupId": "",
			"Name": "身体旋转　X"
		},
		{
			"Id": "ParamBodyAngleY",
			"GroupId": "",
			"Name": "身体旋转　Y"
		},
		{
			"Id": "ParamBodyAngleZ",
			"GroupId": "",
			"Name": "身体旋转　Z"
		},
		{
			"Id": "ParamBreath",
			"GroupId": "",
			"Name": "呼吸"
		},
		{
			"Id": "ParamEyeLSmile",
			"GroupId": "ParamGroup",
			"Name": "左眼　微笑"
		},
		{
			"Id": "ParamEyeRSmile",
			"GroupId": "ParamGroup",
			"Name": "右眼　微笑"
		},
		{
			"Id": "ParamBrowLX",
			"GroupId": "ParamGroup",
			"Name": "左眉　左右"
		},
		{
			"Id": "ParamBrowRX",
			"GroupId": "ParamGroup",
			"Name": "右眉　左右"
		},
		{
			"Id": "ParamBrowLAngle",
			"GroupId": "ParamGroup",
			"Name": "左眉　角度"
		},
		{
			"Id": "ParamBrowRAngle",
			"GroupId": "ParamGroup",
			"Name": "右眉　角度"
		},
		{
			"Id": "ParamBrowLForm",
			"GroupId": "ParamGroup",
			"Name": "左眉　変形"
		},
		{
			"Id": "ParamBrowRForm",
			"GroupId": "ParamGroup",
			"Name": "右眉　変形"
		},
		{
			"Id": "ParamCheek",
			"GroupId": "ParamGroup",
			"Name": "脸颊泛红"
		},
		{
			"Id": "ParamHairFront",
			"GroupId": "ParamGroup",
			"Name": "摇动 前发"
		},
		{
			"Id": "ParamHairSide",
			"GroupId": "ParamGroup",
			"Name": "摇动 侧发"
		},
		{
			"Id": "ParamHairBack",
			"GroupId": "ParamGroup",
			"Name": "摇动 后发"
		}
	],
	"ParameterGroups": [
		{
			"Id": "ParamGroup",
			"GroupId": "",
			"Name": "Folder 1"
		}
	],
	"Parts": [
		{
			"Id": "Part21",
			"Name": "WSQ.psd(未找到对应图层)"
		},
		{
			"Id": "Part16",
			"Name": "WSQ.psd(未找到对应图层)"
		},
		{
			"Id": "Part12",
			"Name": "WSQ.psd(未找到对应图层)"
		},
		{
			"Id": "Part5",
			"Name": "叉手"
		},
		{
			"Id": "Part",
			"Name": "資料夾 1"
		},
		{
			"Id": "Part4",
			"Name": "耳朵2"
		},
		{
			"Id": "Part9",
			"Name": "突出嘴"
		},
		{
			"Id": "Part15",
			"Name": "按键"
		},
		{
			"Id": "Part8",
			"Name": "資料夾 2"
		},
		{
			"Id": "Part10",
			"Name": "按键"
		},
		{
			"Id": "Part11",
			"Name": "資料夾 1"
		},
		{
			"Id": "Part6",
			"Name": "叉手"
		},
		{
			"Id": "Part7",
			"Name": "按键"
		},
		{
			"Id": "Part2",
			"Name": "耳朵"
		},
		{
			"Id": "Part3",
			"Name": "口内"
		}
	]
}